imagerenamer/__init__.py
imagerenamer/cli.py
imagerenamer/core.py
imagerenamer/gui.py
modern_image_renamer-1.1.9.data/scripts/imagerenamer-cli
modern_image_renamer-1.1.9.data/scripts/imagerenamer-gui
modern_image_renamer-1.1.9.dist-info/LICENSE
modern_image_renamer-1.1.9.dist-info/METADATA
modern_image_renamer-1.1.9.dist-info/WHEEL
modern_image_renamer-1.1.9.dist-info/entry_points.txt
modern_image_renamer-1.1.9.dist-info/top_level.txt
modern_image_renamer-1.1.9.dist-info/RECORD
