Metadata-Version: 2.2
Name: modern-image-renamer
Version: 1.1.9
Summary: Rename image files based on their creation date from EXIF metadata
Home-page: https://github.com/larsniet/image-renamer
Author: Lars van der Niet
Author-email: Lars van der Niet <lvdnbusiness@icloud.com>
License: MIT
Project-URL: Homepage, https://github.com/larsniet/image-renamer
Project-URL: Bug Tracker, https://github.com/larsniet/image-renamer/issues
Classifier: Programming Language :: Python :: 3
Classifier: License :: OSI Approved :: MIT License
Classifier: Operating System :: OS Independent
Requires-Python: >=3.6
License-File: LICENSE
Requires-Dist: Pillow>=9.0.0
Requires-Dist: PyQt6>=6.4.0
Dynamic: author
Dynamic: home-page
Dynamic: requires-python
